{
  "id": 133656,
  "name": "Nô Lệ Bóng Tối",
  "slug": "no-le-bong-toi",
  "kind": 1,
  "sex": 1,
  "state": "Đã xuất bản",
  "status": 1,
  "link": "https://metruyencv.com/truyen/no-le-bong-toi",
  "note": "Cầu phiếu đề cử ạ, cảm ơn mọi người ạ.",
  "status_name": "Còn tiếp",
  "first_chapter": 19778148,
  "latest_chapter": 26876588,
  "latest_index": 2818,
  "high_quality": 0,
  "manager_pick": 1,
  "poster": {
    "default": "https://static.cdnno.com/poster/no-le-bong-toi/default.jpg?1731995470",
    "600": "https://static.cdnno.com/poster/no-le-bong-toi/600.jpg?1731995470",
    "300": "https://static.cdnno.com/poster/no-le-bong-toi/300.jpg?1731995470",
    "150": "https://static.cdnno.com/poster/no-le-bong-toi/150.jpg?1731995470"
  },
  "synopsis": "Shadow Slave - Nô Lệ Bóng Tối\n\n[Giới thiệu]\n\nLớn lên trong cảnh nghèo khó, Sunny chưa bao giờ kỳ vọng điều gì tốt đẹp từ cuộc sống. \n\nTuy nhiên, ngay cả cậu cũng không ngờ rằng mình lại được lựa chọn bởi Nightmare Spell (Ác Mộng Ma Pháp) và trở thành một trong những Awakened (Người Thức Tỉnh)– một nhóm tinh anh sở hữu năng lực siêu nhiên. \n\nBị đưa vào một magical world (thế giới ma thuật) đổ nát, Sunny phải đối mặt với những quái vật khủng khiếp – và cả những Người Thức Tỉnh khác – trong một trận chiến sinh tồn chết chóc.\n\nTệ hơn nữa là, sức mạnh thần thánh mà cậu nhận được lại có một tác dụng phụ nhỏ, nhưng có khả năng gây ra tử vong chí mạng…\n\n----\n\nLink wiki Rank/Level: https://docs.google.com/spreadsheets/d/1-0VNavduwb21_G9D_lBvq7mBEs1-UGeWdz197M4MBH8/edit\n\n----\n[CVT - Review và đôi lời]\n\n- Đây là truyện mình sẽ dịch, không phải convert, trang gốc đã ra khoảng hơn 1k9 chương và vẫn còn ra đều, truyện luôn nằm top 1 - 3 các bảng xếp hạng Novel ở phương Tây, về lượt đọc lẫn đánh giá.\n\n-  Đây là một trong những bộ truyện xuất sắc nhất mà mình từng đọc. \n\n- Nhân vật chính lẫn phụ đều vô cùng thông minh, diễn biến tâm lý được khắc họa rất chân thực và sâu sắc. Thế giới trong truyện vô cùng rộng lớn, hệ thống sức mạnh thì mới lạ và độc đáo. Mỗi nhân vật, dù mạnh đến đâu, đều có một điểm yếu gọi là *Flaw* (mình dịch là \"khuyết điểm\" hoặc \"điểm yếu\"). Đặc biệt, mỗi nhân vật đều có năng lực riêng, không ai giống ai cả. \n\n- Nữ chính không phải bình hoa, có cá tính, trí tuệ sức mạnh, mình cực kì thích nhân vật nữ chính, thích cái cách tác giả miêu tả nội tâm nhân vật qua từng thời kỳ, từ niên thiếu cho tới lúc trưởng thành sau này, và tình cảm được hình thành không dễ dàng một tí nào.\n\n- Dàn nhân vật phụ đều có đất diễn, chứ không phải như NPC lướt qua, xây dựng rất đỉnh, đều có chiều sâu.\n\n- Bộ này âm mưu, tình tiết, bố cục rất nhiều, rất sâu, rất nhiều chi tiết từ đầu truyện tưởng chừng như rất bình thường, nhưng thực tế lại không.\n\n- Map rộng, World Building cực kỳ xuất sắc, khá mới, không theo lối mòn, tới chương mới nhất vẫn có rất nhiều điều để khai thác, tóm lại đây là một trong những bộ truyện hay nhất mình từng đọc trong suốt hơn 10 năm qua. Mọi người nên đọc qua khoảng 50-100 chương đầu, hoặc quyển 1, lúc đó sẽ vào mạch truyện và dễ đọc hơn rất nhiều.\n\n---\nMình có thêm một số ảnh minh họa về các nhân vật ở dưới phần hình hảnh, gần chỗ bình luận.\n\n---\nDanh sách các quyển đã dịch:\n\nQuyển 1 - [Đứa Con Của Bóng Tối] - [Chương 1 - > Chương 95]\nQuyển 2 - [Con Quỷ Của Sự Thay Đổi] - [Chương 96 - > Chương 350]\nQuyển 3 - [Quần Đảo Xiềng Xích] - [Chương 351 - > Chương 600]\nQuyển 4 - [Kẻ Phá Vỡ Xiềng Xích] - [Chương 601 - > Chương 750]\nQuyển 5 - [Đêm Kinh Hoàng] - [Chương 751 - > Chương 1060]\nQuyển 6 - [Tất Cả Ác Quỷ Đã Đến] - [Chương 1061 --> Chương 1230]\nQuyển 7 - [Lăng Mộ Của Ariel] - [Chương 1231 --> Chương 1590]\nQuyển 8 - [Lord Shadow (Chúa Tể Bóng Tối)] - [Chương 1591--> Chương 1840]\nQuyển 9 - [Throne of War (Ngai Vàng Chiến Tranh] - [Chương 1841--> Chương 2260]\nQuyển 10 - [Dark Lord's Dreadful Travelogue (Hành Trình Đáng Sợ Của Chúa Tể Bóng Tối)] - [Chương 2261--> Chương 2720]\n                - Phần I: 2261 - 2409\n                - Phần II: 2410 - 2550\n                - Phần III: 2551 - 2720",
  "vote_count": 38696,
  "review_score": "4.960",
  "review_count": 332,
  "comment_count": 5438,
  "chapter_count": 2818,
  "view_count": 0,
  "word_count": 4364428,
  "created_at": "2024-10-13T08:48:09.000000Z",
  "updated_at": "2026-02-18T13:30:22.000000Z",
  "new_chap_at": "2026-02-12T04:29:42.000000Z",
  "published_at": "2024-10-13T08:48:09.000000Z",
  "published": 1,
  "user_id": 1000045,
  "object_type": "Book",
  "report_options": [
    {
      "title": "Báo cáo truyện Nô Lệ Bóng Tối",
      "assign_to": "editor",
      "content_placeholder": "Vui lòng cung cấp thông tin chi tiết về lỗi hoặc vi phạm của truyện"
    }
  ],
  "bookmark_count": 14952,
  "chapter_per_week": 4,
  "ready_for_sale": 0,
  "discount_price": 0,
  "discount": 0,
  "creator": {
    "id": 1000045,
    "name": "Thanh Hưng",
    "avatar": [
      "https://static.cdnno.com/user/c79de127d8c211a21898811f1e74d3f5/200.jpg?1590805499",
      "https://static.cdnno.com/user/c79de127d8c211a21898811f1e74d3f5/100.jpg?1590805499",
      "https://static.cdnno.com/user/c79de127d8c211a21898811f1e74d3f5/50.jpg?1590805499"
    ],
    "level": 3,
    "exp": 584,
    "object_type": "User"
  },
  "author": {
    "id": 18437,
    "name": "Guiltythree",
    "avatar": null,
    "local_name": "Guiltythree",
    "object_type": "Author"
  },
  "genres": [
    {
      "id": 20,
      "name": "Kỳ Ảo",
      "object_type": "Genre"
    }
  ],
  "tags": [
    {
      "id": 6,
      "name": "Cơ Trí",
      "type_id": "1",
      "object_type": "Tag"
    },
    {
      "id": 15,
      "name": "Tây Phương Kỳ Huyễn",
      "type_id": "2",
      "object_type": "Tag"
    },
    {
      "id": 61,
      "name": "Phàm Nhân",
      "type_id": "3",
      "object_type": "Tag"
    },
    {
      "id": 86,
      "name": "Góc Nhìn Nam",
      "type_id": "4",
      "object_type": "Tag"
    }
  ]
}