{
  "id": 114714,
  "name": "Vừa Thành Tiên Thần, Con Cháu Cầu Ta Xuất Sơn",
  "slug": "vua-thanh-tien-than-con-chau-cau-ta-dang-co",
  "kind": 1,
  "sex": 1,
  "state": "Đã xuất bản",
  "status": 2,
  "link": "https://metruyencv.com/truyen/vua-thanh-tien-than-con-chau-cau-ta-dang-co",
  "note": "",
  "status_name": "Hoàn thành",
  "first_chapter": 15357120,
  "latest_chapter": 16821188,
  "latest_index": 787,
  "high_quality": 0,
  "manager_pick": 1,
  "poster": {
    "default": "https://static.cdnno.com/poster/vua-thanh-tien-than-con-chau-cau-ta-dang-co/default.jpg?1665195835",
    "600": "https://static.cdnno.com/poster/vua-thanh-tien-than-con-chau-cau-ta-dang-co/600.jpg?1665195835",
    "300": "https://static.cdnno.com/poster/vua-thanh-tien-than-con-chau-cau-ta-dang-co/300.jpg?1665195835",
    "150": "https://static.cdnno.com/poster/vua-thanh-tien-than-con-chau-cau-ta-dang-co/150.jpg?1665195835"
  },
  "synopsis": "\tĐầu thai trở thành Cảnh triều lập quốc vị thứ nhất Thái Tử, Khương Trường Sinh vừa ra đời liền bị gian nhân đánh tráo, sau được đưa đến một đạo quan bên trong, trở thành một tên bình thường tiểu đạo sĩ.\r\n\r\n\tTheo Thái Tử đến không người hỏi thăm tiểu đạo sĩ, nhân sinh rơi xuống, cũng may Khương Trường Sinh mở ra sinh tồn hệ thống, vô hạn tuổi thọ, chỉ cần vượt qua nhân sinh gặp trắc trở, liền có thể đạt được  sinh tồn ban thưởng.\r\n\r\n\tKém chút bị sư huynh luyện công ngộ sát, may mắn sống sót, thu hoạch được Thần Ảnh thối.\r\n\r\n\tTao ngộ địa chấn, hiểm bị xà nhà đập chết, thu hoạch được Cửu Tầm Thiên Long Bộ.\r\n\r\n\tYêu ma tứ loạn Kinh Thành, bình an vượt qua, lấy được pháp bảo Hàng Ma xử.\r\n\r\n\t. . .\r\n\r\n\tVương triều san sát, yêu ma hoành hành, võ đạo trấn thế, đây là một cái không có tiên thần thế giới, đạo pháp ẩn vào triều đình, rừng núi.\r\n\r\n\tBa trăm năm sau.\r\n\r\n\tCảnh triều tại cường thịnh lúc nghênh đón suy vong, chư hầu cùng xuất hiện, Thiên Tử biến thành kiêu hùng trong tay khôi lỗi, phân liệt vương triều, chinh phạt hơn mười năm, quốc lực hạ xuống thấp nhất, xung quanh dị tộc thừa cơ xâm lấn, dân chúng lầm than, nhân gian hóa thành địa ngục.\r\n\r\n\tHoàng đế bù nhìn Khương Huyền Chân đi vào đạo quan trước, quỳ lạy thút thít: \"Con cháu bất hiếu, vô lực hồi thiên, thỉnh tổ tông đăng cơ, lại nối tiếp ta Đại Cảnh 300 năm!\"\r\n\r\nCảnh giới Võ đạo: Tam Lưu, Nhị Lưu, Nhất Lưu, Chân Nguyên, Linh Thức, Thông Thiên, Thần Tâm, Thần Nhân, Kim Thân, Càn Khôn...",
  "vote_count": 36851,
  "review_score": "4.910",
  "review_count": 431,
  "comment_count": 17353,
  "chapter_count": 787,
  "view_count": 0,
  "word_count": 2070664,
  "created_at": "2022-10-08T02:23:29.000000Z",
  "updated_at": "2026-02-16T16:49:36.000000Z",
  "new_chap_at": "2023-09-26T11:11:00.000000Z",
  "published_at": "2022-10-08T02:23:29.000000Z",
  "published": 1,
  "user_id": 1000043,
  "object_type": "Book",
  "report_options": [
    {
      "title": "Báo cáo truyện Vừa Thành Tiên Thần, Con Cháu Cầu Ta Xuất Sơn",
      "assign_to": "editor",
      "content_placeholder": "Vui lòng cung cấp thông tin chi tiết về lỗi hoặc vi phạm của truyện"
    }
  ],
  "bookmark_count": 8012,
  "chapter_per_week": 0,
  "ready_for_sale": 0,
  "discount_price": 0,
  "discount": 0,
  "creator": {
    "id": 1000043,
    "name": "KOL",
    "avatar": [
      "https://static.cdnno.com/user/ca984adb8b7a66287718584d2eb27742/200.jpg?1586581800",
      "https://static.cdnno.com/user/ca984adb8b7a66287718584d2eb27742/100.jpg?1586581800",
      "https://static.cdnno.com/user/ca984adb8b7a66287718584d2eb27742/50.jpg?1586581800"
    ],
    "level": 1,
    "exp": 57,
    "object_type": "User"
  },
  "author": {
    "id": 665,
    "name": "Nhâm Ngã Tiếu",
    "avatar": null,
    "local_name": "任我笑",
    "object_type": "Author"
  },
  "genres": [
    {
      "id": 2,
      "name": "Tiên Hiệp",
      "object_type": "Genre"
    }
  ],
  "tags": [
    {
      "id": 1,
      "name": "Điềm Đạm",
      "type_id": "1",
      "object_type": "Tag"
    },
    {
      "id": 11,
      "name": "Đông Phương Huyền Huyễn",
      "type_id": "2",
      "object_type": "Tag"
    },
    {
      "id": 62,
      "name": "Vô Địch",
      "type_id": "3",
      "object_type": "Tag"
    },
    {
      "id": 86,
      "name": "Góc Nhìn Nam",
      "type_id": "4",
      "object_type": "Tag"
    }
  ]
}